scrapy_plyvel/__init__.py
scrapy_plyvel/httpcache.py
scrapy_plyvel-0.1.1.dist-info/WHEEL
scrapy_plyvel-0.1.1.dist-info/METADATA
scrapy_plyvel-0.1.1.dist-info/RECORD
