Metadata-Version: 2.1
Name: scrapy-plyvel
Version: 0.1.1
Summary: Scrapy cache storage using plyvel
Home-page: https://github.com/ratson/scrapy-plyvel
License: MIT
Author: Ratson
Author-email: github@ratson.name
Requires-Python: >=3.7,<4.0
Classifier: Development Status :: 2 - Pre-Alpha
Classifier: Environment :: Plugins
Classifier: Framework :: Scrapy
Classifier: Intended Audience :: Developers
Classifier: License :: OSI Approved :: MIT License
Classifier: Operating System :: OS Independent
Classifier: Programming Language :: Python
Classifier: Programming Language :: Python :: 3
Classifier: Programming Language :: Python :: 3.7
Classifier: Topic :: Internet :: WWW/HTTP
Classifier: Topic :: Software Development :: Libraries :: Python Modules
Requires-Dist: plyvel (>=1.0,<2.0)
Project-URL: Repository, https://github.com/ratson/scrapy-plyvel
